compare_version_strings/__init__.py
compare_version_strings/compare_version_strings.py
compare_version_strings/tests/__init__.py
compare_version_strings/tests/abdulqahhar_aminujatto_test.py
jatto_compare_version_strings-0.0.1.dist-info/METADATA
jatto_compare_version_strings-0.0.1.dist-info/WHEEL
jatto_compare_version_strings-0.0.1.dist-info/top_level.txt
jatto_compare_version_strings-0.0.1.dist-info/RECORD
