Metadata-Version: 2.1
Name: jatto-compare-version-strings
Version: 0.0.1
Summary: Compare version strings
Home-page: https://github.com/jattoabdul/compare_version_strings
Author: Aminujatto Abdulqahhar
Author-email: jattoade@gmail.com
License: MIT
Platform: UNKNOWN
